bar/__init__.py
bar/speaker.py
coding_test_foo-2.0.0.dist-info/METADATA
coding_test_foo-2.0.0.dist-info/WHEEL
coding_test_foo-2.0.0.dist-info/top_level.txt
coding_test_foo-2.0.0.dist-info/RECORD
